ergs_selector/__init__.py
ergs_selector/ergs.py
ergs_selector-0.1.2.dist-info/licenses/LICENSE
ergs_selector-0.1.2.dist-info/METADATA
ergs_selector-0.1.2.dist-info/WHEEL
ergs_selector-0.1.2.dist-info/top_level.txt
ergs_selector-0.1.2.dist-info/RECORD
