Metadata-Version: 2.4
Name: ergs-selector
Version: 0.1.2
Summary: Effective Range-based Feature Selection (ERGS) for Classification
Home-page: https://github.com/yourusername/ergs-selector
Author: Manoj Kumar
Author-email: manojkumar.du.or.21@gmail.com
Classifier: Programming Language :: Python :: 3
Classifier: License :: OSI Approved :: MIT License
Requires-Python: >=3.6
License-File: LICENSE
Requires-Dist: numpy
Requires-Dist: pandas
Requires-Dist: scikit-learn
Dynamic: author
Dynamic: author-email
Dynamic: classifier
Dynamic: description
Dynamic: description-content-type
Dynamic: home-page
Dynamic: license-file
Dynamic: requires-dist
Dynamic: requires-python
Dynamic: summary
